{
  "className": "org.joget.apps.form.model.Form",
  "properties": {
    "id": "mm_field",
    "name": "MM - Field",
    "tableName": "mm_field",
    "description": "A single input or display element on a screen. Per RegBB spec \u00a74.1.6 / \u00a77.2.8. Lesotho extension per D9: widget=repeating_group with childScreenId + min/max rows + add/remove labels.",
    "loadBinder": {
      "className": "org.joget.apps.form.lib.WorkflowFormBinder",
      "properties": {}
    },
    "storeBinder": {
      "className": "org.joget.apps.form.lib.WorkflowFormBinder",
      "properties": {}
    },
    "permission": {
      "className": "",
      "properties": {}
    },
    "noPermissionMessage": "",
    "postProcessor": {
      "className": "",
      "properties": {}
    },
    "postProcessorRunOn": "create"
  },
  "elements": [
    {
      "className": "org.joget.apps.form.model.Section",
      "properties": {
        "id": "identitySection",
        "label": "Identity"
      },
      "elements": [
        {
          "className": "org.joget.apps.form.model.Column",
          "properties": {
            "width": "50%"
          },
          "elements": [
            {
              "className": "org.joget.apps.form.lib.HiddenField",
              "properties": {
                "id": "screenId",
                "label": "Parent Screen",
                "value": "",
                "useDefaultWhenEmpty": "true",
                "workflowVariable": ""
              }
            },
            {
              "className": "org.joget.apps.form.lib.TextField",
              "properties": {
                "id": "orderIndex",
                "label": "Order Index",
                "size": "8",
                "value": "0",
                "validator": {
                  "className": "org.joget.apps.form.lib.DefaultValidator",
                  "properties": {
                    "mandatory": "true",
                    "type": "integer",
                    "message": ""
                  }
                }
              }
            },
            {
              "className": "org.joget.apps.form.lib.TextField",
              "properties": {
                "id": "storageKey",
                "label": "Storage Key (path inside dataJson)",
                "size": "64",
                "validator": {
                  "className": "org.joget.apps.form.lib.DefaultValidator",
                  "properties": {
                    "mandatory": "true",
                    "type": "",
                    "message": ""
                  }
                }
              }
            },
            {
              "className": "org.joget.apps.form.lib.TextField",
              "properties": {
                "id": "label",
                "label": "Display Label",
                "size": "255",
                "validator": {
                  "className": "org.joget.apps.form.lib.DefaultValidator",
                  "properties": {
                    "mandatory": "true",
                    "type": "",
                    "message": ""
                  }
                }
              }
            }
          ]
        },
        {
          "className": "org.joget.apps.form.model.Column",
          "properties": {
            "width": "50%"
          },
          "elements": [
            {
              "className": "org.joget.apps.form.lib.SelectBox",
              "properties": {
                "id": "widget",
                "label": "Widget",
                "options": [
                  {
                    "value": "text",
                    "label": "Text",
                    "grouping": ""
                  },
                  {
                    "value": "number",
                    "label": "Number",
                    "grouping": ""
                  },
                  {
                    "value": "date",
                    "label": "Date",
                    "grouping": ""
                  },
                  {
                    "value": "select",
                    "label": "Select (dropdown)",
                    "grouping": ""
                  },
                  {
                    "value": "radio",
                    "label": "Radio",
                    "grouping": ""
                  },
                  {
                    "value": "checkbox",
                    "label": "Checkbox",
                    "grouping": ""
                  },
                  {
                    "value": "textarea",
                    "label": "Textarea",
                    "grouping": ""
                  },
                  {
                    "value": "file_upload",
                    "label": "File Upload",
                    "grouping": ""
                  },
                  {
                    "value": "gis_polygon",
                    "label": "GIS Polygon",
                    "grouping": ""
                  },
                  {
                    "value": "signature",
                    "label": "Signature",
                    "grouping": ""
                  },
                  {
                    "value": "qr_scan",
                    "label": "QR Scan",
                    "grouping": ""
                  },
                  {
                    "value": "repeating_group",
                    "label": "Repeating Group (per D9)",
                    "grouping": ""
                  }
                ],
                "optionsBinder": {
                  "className": "",
                  "properties": {}
                },
                "validator": {
                  "className": "org.joget.apps.form.lib.DefaultValidator",
                  "properties": {
                    "mandatory": "true",
                    "type": "",
                    "message": ""
                  }
                }
              }
            },
            {
              "className": "org.joget.apps.form.lib.SelectBox",
              "properties": {
                "id": "dataType",
                "label": "Data Type",
                "options": [
                  {
                    "value": "string",
                    "label": "String",
                    "grouping": ""
                  },
                  {
                    "value": "number",
                    "label": "Number",
                    "grouping": ""
                  },
                  {
                    "value": "date",
                    "label": "Date",
                    "grouping": ""
                  },
                  {
                    "value": "boolean",
                    "label": "Boolean",
                    "grouping": ""
                  }
                ],
                "optionsBinder": {
                  "className": "",
                  "properties": {}
                },
                "value": "string",
                "validator": {
                  "className": "org.joget.apps.form.lib.DefaultValidator",
                  "properties": {
                    "mandatory": "true",
                    "type": "",
                    "message": ""
                  }
                }
              }
            },
            {
              "className": "org.joget.apps.form.lib.TextField",
              "properties": {
                "id": "claimType",
                "label": "Claim Type (e.g. applicant.dateOfBirth)",
                "size": "64",
                "validator": {
                  "className": "",
                  "properties": {}
                }
              }
            },
            {
              "className": "org.joget.apps.form.lib.SelectBox",
              "properties": {
                "id": "defaultBehaviorOnError",
                "label": "Default Behaviour on Determinant Error",
                "options": [
                  {
                    "value": "visible",
                    "label": "Visible",
                    "grouping": ""
                  },
                  {
                    "value": "hidden",
                    "label": "Hidden",
                    "grouping": ""
                  },
                  {
                    "value": "required",
                    "label": "Required",
                    "grouping": ""
                  },
                  {
                    "value": "optional",
                    "label": "Optional",
                    "grouping": ""
                  }
                ],
                "optionsBinder": {
                  "className": "",
                  "properties": {}
                },
                "value": "optional",
                "validator": {
                  "className": "",
                  "properties": {}
                }
              }
            },
            {
              "className": "org.joget.apps.form.lib.SelectBox",
              "properties": {
                "id": "displayOnList",
                "label": "Show in datalist (operator inbox / citizen overview)",
                "options": [
                  {
                    "value": "N",
                    "label": "No (default)",
                    "grouping": ""
                  },
                  {
                    "value": "Y",
                    "label": "Yes",
                    "grouping": ""
                  }
                ],
                "optionsBinder": {
                  "className": "",
                  "properties": {}
                },
                "value": "N",
                "validator": {
                  "className": "",
                  "properties": {}
                }
              }
            }
          ]
        }
      ]
    },
    {
      "className": "org.joget.apps.form.model.Section",
      "properties": {
        "id": "lookupAndActionsSection",
        "label": "Lookup, Determinants, Actions"
      },
      "elements": [
        {
          "className": "org.joget.apps.form.model.Column",
          "properties": {
            "width": "50%"
          },
          "elements": [
            {
              "className": "org.joget.apps.form.lib.SelectBox",
              "properties": {
                "id": "optionsCatalogId",
                "label": "Options Catalog (for select / radio / checkbox)",
                "options": [],
                "optionsBinder": {
                  "className": "org.joget.apps.form.lib.FormOptionsBinder",
                  "properties": {
                    "formDefId": "mm_catalog",
                    "idColumn": "code",
                    "labelColumn": "name",
                    "groupingColumn": "",
                    "extraCondition": "",
                    "addEmptyOption": "true",
                    "emptyLabel": "(none)",
                    "useAjax": "",
                    "cacheInterval": ""
                  }
                },
                "validator": {
                  "className": "",
                  "properties": {}
                }
              }
            },
            {
              "className": "org.joget.apps.form.lib.TextArea",
              "properties": {
                "id": "optionsBinderJson",
                "label": "Options Binder JSON (alternative to catalog; e.g. registry-sourced)",
                "rows": "3",
                "cols": "40",
                "validator": {
                  "className": "",
                  "properties": {}
                }
              }
            },
            {
              "className": "org.joget.apps.form.lib.TextField",
              "properties": {
                "id": "optionsFilterField",
                "label": "Options Filter Field (cascading dropdown — parent field id)",
                "size": "64",
                "placeholder": "e.g. \"district\" — for a village select that filters by selected district",
                "validator": {
                  "className": "",
                  "properties": {}
                }
              }
            },
            {
              "className": "org.joget.apps.form.lib.TextField",
              "properties": {
                "id": "visibilityDeterminantId",
                "label": "Visibility Determinant ID (optional)",
                "size": "64",
                "validator": {
                  "className": "",
                  "properties": {}
                }
              }
            },
            {
              "className": "org.joget.apps.form.lib.TextField",
              "properties": {
                "id": "requirednessDeterminantId",
                "label": "Requiredness Determinant ID (optional)",
                "size": "64",
                "validator": {
                  "className": "",
                  "properties": {}
                }
              }
            }
          ]
        },
        {
          "className": "org.joget.apps.form.model.Column",
          "properties": {
            "width": "50%"
          },
          "elements": [
            {
              "className": "org.joget.apps.form.lib.TextArea",
              "properties": {
                "id": "registrationIds",
                "label": "Registration IDs (semicolon-separated FK list)",
                "rows": "2",
                "cols": "40",
                "validator": {
                  "className": "",
                  "properties": {}
                }
              }
            },
            {
              "className": "org.joget.apps.form.lib.TextArea",
              "properties": {
                "id": "actionIds",
                "label": "Action IDs (semicolon-separated FK list)",
                "rows": "2",
                "cols": "40",
                "validator": {
                  "className": "",
                  "properties": {}
                }
              }
            },
            {
              "className": "org.joget.apps.form.lib.TextArea",
              "properties": {
                "id": "validationRulesJson",
                "label": "Validation Rules JSON (regex, length, range)",
                "rows": "3",
                "cols": "40",
                "validator": {
                  "className": "",
                  "properties": {}
                }
              }
            },
            {
              "className": "org.joget.apps.form.lib.TextArea",
              "properties": {
                "id": "widgetConfig",
                "label": "Widget Config JSON (per-widget overrides; per kernel SAD §8)",
                "rows": "4",
                "cols": "40",
                "placeholder": "{ \"defaultZoom\": 15, \"mapHeight\": 500 }  — see kernel SAD for the per-widget allowlist.",
                "validator": {
                  "className": "",
                  "properties": {}
                }
              }
            },
            {
              "className": "org.joget.apps.form.lib.TextField",
              "properties": {
                "id": "helpText",
                "label": "Help Text",
                "size": "255",
                "validator": {
                  "className": "",
                  "properties": {}
                }
              }
            }
          ]
        }
      ]
    },
    {
      "className": "org.joget.apps.form.model.Section",
      "properties": {
        "id": "repeatingGroupSection",
        "label": "Repeating Group Settings (when widget=repeating_group, per D9)"
      },
      "elements": [
        {
          "className": "org.joget.apps.form.model.Column",
          "properties": {
            "width": "50%"
          },
          "elements": [
            {
              "className": "org.joget.apps.form.lib.TextField",
              "properties": {
                "id": "referencedFormId",
                "label": "Referenced Joget Form ID (for widget=repeating_group; e.g. householdMemberForm)",
                "size": "64",
                "placeholder": "householdMemberForm",
                "validator": {
                  "className": "",
                  "properties": {}
                }
              }
            },
            {
              "className": "org.joget.apps.form.lib.SelectBox",
              "properties": {
                "id": "childScreenId",
                "label": "Child Screen (defines repeating row's structure)",
                "options": [],
                "optionsBinder": {
                  "className": "org.joget.apps.form.lib.FormOptionsBinder",
                  "properties": {
                    "formDefId": "mm_screen",
                    "idColumn": "code",
                    "labelColumn": "title",
                    "groupingColumn": "",
                    "extraCondition": "",
                    "addEmptyOption": "true",
                    "emptyLabel": "(n/a)",
                    "useAjax": "",
                    "cacheInterval": ""
                  }
                },
                "validator": {
                  "className": "",
                  "properties": {}
                }
              }
            },
            {
              "className": "org.joget.apps.form.lib.TextField",
              "properties": {
                "id": "minRows",
                "label": "Min Rows",
                "size": "8",
                "value": "0",
                "validator": {
                  "className": "org.joget.apps.form.lib.DefaultValidator",
                  "properties": {
                    "mandatory": "false",
                    "type": "integer",
                    "message": ""
                  }
                }
              }
            },
            {
              "className": "org.joget.apps.form.lib.TextField",
              "properties": {
                "id": "maxRows",
                "label": "Max Rows (blank = unlimited)",
                "size": "8",
                "validator": {
                  "className": "org.joget.apps.form.lib.DefaultValidator",
                  "properties": {
                    "mandatory": "false",
                    "type": "integer",
                    "message": ""
                  }
                }
              }
            }
          ]
        },
        {
          "className": "org.joget.apps.form.model.Column",
          "properties": {
            "width": "50%"
          },
          "elements": [
            {
              "className": "org.joget.apps.form.lib.TextField",
              "properties": {
                "id": "addLabel",
                "label": "Add Button Label",
                "size": "64",
                "value": "Add row",
                "validator": {
                  "className": "",
                  "properties": {}
                }
              }
            },
            {
              "className": "org.joget.apps.form.lib.TextField",
              "properties": {
                "id": "removeLabel",
                "label": "Remove Button Label",
                "size": "64",
                "value": "Remove",
                "validator": {
                  "className": "",
                  "properties": {}
                }
              }
            }
          ]
        }
      ]
    }
  ]
}